tick/__init__.py
tick/array/__init__.py
tick/array/serialize.py
tick/array/build/__init__.py
tick/array/build/_array.cp37-win_amd64.exp
tick/array/build/_array.cp37-win_amd64.lib
tick/array/build/_array.cp37-win_amd64.pyd
tick/array/build/array.py
tick/array/tests/__init__.py
tick/array/tests/serialize_test.py
tick/array_test/__init__.py
tick/array_test/build/__init__.py
tick/array_test/build/_array_test.cp37-win_amd64.exp
tick/array_test/build/_array_test.cp37-win_amd64.lib
tick/array_test/build/_array_test.cp37-win_amd64.pyd
tick/array_test/build/array_test.py
tick/array_test/tests/__init__.py
tick/array_test/tests/array_memory_test.py
tick/array_test/tests/array_methods_test.py
tick/array_test/tests/array_performance_test.py
tick/array_test/tests/array_typemap_test.py
tick/base/__init__.py
tick/base/base.py
tick/base/decorators.py
tick/base/dtype_to_cpp_type.py
tick/base/inference.py
tick/base/opsys.py
tick/base/threadpool.py
tick/base/timefunc.py
tick/base/build/__init__.py
tick/base/build/_base.cp37-win_amd64.exp
tick/base/build/_base.cp37-win_amd64.lib
tick/base/build/_base.cp37-win_amd64.pyd
tick/base/build/base.py
tick/base/learner/__init__.py
tick/base/learner/learner_glm.py
tick/base/learner/learner_optim.py
tick/base/simulation/__init__.py
tick/base/simulation/simu.py
tick/base/simulation/simu_with_features.py
tick/base/tests/__init__.py
tick/base/tests/base_test.py
tick/base/tests/decorators_test.py
tick/base/tests/exceptions_test.py
tick/base/tests/standard_normal_distribution_test.py
tick/base/tests/time_func_pickle_test.py
tick/base/tests/time_func_test.py
tick/base_model/__init__.py
tick/base_model/model.py
tick/base_model/model_first_order.py
tick/base_model/model_generalized_linear.py
tick/base_model/model_labels_features.py
tick/base_model/model_lipschitz.py
tick/base_model/model_second_order.py
tick/base_model/model_self_concordant.py
tick/base_model/build/__init__.py
tick/base_model/build/_base_model.cp37-win_amd64.exp
tick-0.6.0.1.dist-info/LICENSE.txt
tick-0.6.0.1.dist-info/METADATA
tick-0.6.0.1.dist-info/WHEEL
tick-0.6.0.1.dist-info/top_level.txt
tick-0.6.0.1.dist-info/RECORD
