Metadata-Version: 2.1
Name: tick
Version: 0.6.0.1
Summary: Module for statistical learning, with a particular emphasis on time-dependent modelling
Home-page: https://x-datainitiative.github.io/tick/
Author: Emmanuel Bacry, Stephane Gaiffas, Martin Bompaire, Søren V. Poulsen, Maryan Morel, Simon Bussy, Philip Deegan
Author-email: martin.bompaire@polytechnique.edu, philip.deegan@polytechnique.edu
License: UNKNOWN
Platform: UNKNOWN
Classifier: Development Status :: 3 - Alpha
Classifier: Intended Audience :: Science/Research
Classifier: Intended Audience :: Developers
Classifier: Programming Language :: C++
Classifier: Programming Language :: Python
Classifier: Topic :: Software Development
Classifier: Topic :: Scientific/Engineering
Classifier: Operating System :: POSIX
Classifier: Operating System :: Unix
Classifier: Operating System :: MacOS
Classifier: Programming Language :: Python :: 3.5
Classifier: Programming Language :: Python :: 3.6
Classifier: Programming Language :: Python :: 3.7
Classifier: License :: OSI Approved :: BSD License
Requires-Dist: numpy
Requires-Dist: scipy
Requires-Dist: numpydoc
Requires-Dist: matplotlib
Requires-Dist: sphinx
Requires-Dist: pandas
Requires-Dist: dill
Requires-Dist: scikit-learn
